lymph-0.14.0-py2.7-nspkg.pth
lymph/autodoc.py
lymph/autoreload.py
lymph/client.py
lymph/config.py
lymph/exceptions.py
lymph/monkey.py
lymph/cli/__init__.py
lymph/cli/base.py
lymph/cli/config.py
lymph/cli/discover.py
lymph/cli/emit.py
lymph/cli/help.py
lymph/cli/inspect.py
lymph/cli/list.py
lymph/cli/loglevel.py
lymph/cli/main.py
lymph/cli/request.py
lymph/cli/service.py
lymph/cli/shell.py
lymph/cli/subscribe.py
lymph/cli/tail.py
lymph/cli/testing.py
lymph/cli/tests/__init__.py
lymph/cli/tests/test_testing.py
lymph/core/__init__.py
lymph/core/channels.py
lymph/core/components.py
lymph/core/connection.py
lymph/core/container.py
lymph/core/declarations.py
lymph/core/decorators.py
lymph/core/events.py
lymph/core/interfaces.py
lymph/core/messages.py
lymph/core/plugins.py
lymph/core/rpc.py
lymph/core/services.py
lymph/core/trace.py
lymph/core/versioning.py
lymph/core/monitoring/__init__.py
lymph/core/monitoring/aggregator.py
lymph/core/monitoring/global_metrics.py
lymph/core/monitoring/metrics.py
lymph/core/monitoring/pusher.py
lymph/core/tests/__init__.py
lymph/core/tests/test_events.py
lymph/discovery/__init__.py
lymph/discovery/base.py
lymph/discovery/static.py
lymph/discovery/zookeeper.py
lymph/events/__init__.py
lymph/events/base.py
lymph/events/kombu.py
lymph/events/local.py
lymph/events/null.py
lymph/patterns/__init__.py
lymph/patterns/serial_events.py
lymph/plugins/__init__.py
lymph/plugins/newrelic.py
lymph/plugins/sentry.py
lymph/serializers/__init__.py
lymph/serializers/base.py
lymph/serializers/kombu.py
lymph/serializers/tests/__init__.py
lymph/serializers/tests/test_base.py
lymph/services/__init__.py
lymph/services/node.py
lymph/services/scheduler.py
lymph/testing/__init__.py
lymph/testing/mock_helpers.py
lymph/testing/nose.py
lymph/testing/pytest.py
lymph/tests/__init__.py
lymph/tests/test_config.py
lymph/tests/test_mock_helpers.py
lymph/tests/test_mockcontainer.py
lymph-0.14.0.dist-info/DESCRIPTION.rst
lymph-0.14.0.dist-info/entry_points.txt
lymph-0.14.0.dist-info/METADATA
lymph-0.14.0.dist-info/metadata.json
lymph-0.14.0.dist-info/namespace_packages.txt
lymph-0.14.0.dist-info/RECORD
lymph-0.14.0.dist-info/top_level.txt
lymph-0.14.0.dist-info/WHEEL
