Metadata-Version: 2.0
Name: lymph
Version: 0.14.0
Summary: a service framework
Home-page: http://github.com/deliveryhero/lymph/
Author: Johannes Dollinger
Author-email: johannes.dollinger@deliveryhero.com
License: Apache License (2.0)
Platform: UNKNOWN
Classifier: Development Status :: 3 - Alpha
Classifier: Intended Audience :: Developers
Classifier: License :: OSI Approved :: Apache Software License
Classifier: Operating System :: OS Independent
Classifier: Programming Language :: Python :: 2.7
Classifier: Programming Language :: Python :: 3
Requires-Dist: docopt (>=0.6.1)
Requires-Dist: kazoo (>=1.3.1)
Requires-Dist: kombu (>=3.0.16)
Requires-Dist: gevent (>=1.0.2)
Requires-Dist: msgpack-python (>=0.4.0)
Requires-Dist: psutil (>=2.1.1)
Requires-Dist: PyYAML (>=3.11)
Requires-Dist: pyzmq (>=14.3.0)
Requires-Dist: redis (>=2.9.1)
Requires-Dist: setproctitle (>=1.1.8)
Requires-Dist: six (>=1.6)
Requires-Dist: Werkzeug (>=0.10.4)
Requires-Dist: blessings (>=1.5.1)
Requires-Dist: netifaces (>=0.10.4)
Requires-Dist: mock (>=1.0.1)
Requires-Dist: PyHamcrest (>=1.8.2)
Requires-Dist: pytz (>=2015.4)
Requires-Dist: iso8601 (>=0.1.10)
Requires-Dist: semantic-version (>=2.4.2)
Requires-Dist: Monotime (>=1.0)
Provides-Extra: newrelic
Requires-Dist: newrelic; extra == 'newrelic'
Provides-Extra: sentry
Requires-Dist: raven; extra == 'sentry'
